<?xml version="1.0" encoding="UTF-8"?>
<MF0 version="1.1" packageUris="http://schema.mathworks.com/mf0/ci/19700101 http://schema.mathworks.com/mf0/sl_modelref_info/R2021a http://schema.mathworks.com/mf0/slexec_mm_sto/R2021a_202007071525">
  <ModelRefInfoRepo.ModelRefInfoRoot type="ModelRefInfoRepo.ModelRefInfoRoot" uuid="297945a6-3b18-43b8-b13a-bc1ed2539a48">
    <autoSolverStatusFlags>333</autoSolverStatusFlags>
    <childModelRefInfo type="ModelRefInfoRepo.ChildModelRefInfo" uuid="a66ecdd6-98c6-4b6f-bec2-e0c6835a001e">
      <modelName>Animation_Recorder</modelName>
      <modelPath>Animation_Recorder</modelPath>
    </childModelRefInfo>
    <compDerivCacheNeedsReset>false</compDerivCacheNeedsReset>
    <compZcCacheNeedsReset>false</compZcCacheNeedsReset>
    <dataTransferInfos>AAFJTQAAAAAOAAAAOAAAAAYAAAAIAAAAAgAAAAAAAAAFAAAACAAAAAAAAAABAAAAAQAAAAAAAAAFAAQAAQAAAAEAAAAAAAAA</dataTransferInfos>
    <defaultsCMapping>{&quot;Inports&quot;:&quot;{\&quot;Name\&quot;:\&quot;Default\&quot;,\&quot;Checksum\&quot;:\&quot;Default\&quot;,\&quot;PerInstancePropertiesChecksum\&quot;:\&quot;\&quot;,\&quot;MemorySectionName\&quot;:\&quot;None\&quot;,\&quot;MemorySectionChecksum\&quot;:\&quot;None\&quot;}&quot;,&quot;Outports&quot;:&quot;{\&quot;Name\&quot;:\&quot;Default\&quot;,\&quot;Checksum\&quot;:\&quot;Default\&quot;,\&quot;PerInstancePropertiesChecksum\&quot;:\&quot;\&quot;,\&quot;MemorySectionName\&quot;:\&quot;None\&quot;,\&quot;MemorySectionChecksum\&quot;:\&quot;None\&quot;}&quot;,&quot;ParameterArguments&quot;:&quot;{\&quot;Name\&quot;:\&quot;Default\&quot;,\&quot;Checksum\&quot;:\&quot;Default\&quot;,\&quot;PerInstancePropertiesChecksum\&quot;:\&quot;\&quot;,\&quot;MemorySectionName\&quot;:\&quot;None\&quot;,\&quot;MemorySectionChecksum\&quot;:\&quot;None\&quot;}&quot;,&quot;LocalParameters&quot;:&quot;{\&quot;Name\&quot;:\&quot;Default\&quot;,\&quot;Checksum\&quot;:\&quot;Default\&quot;,\&quot;PerInstancePropertiesChecksum\&quot;:\&quot;\&quot;,\&quot;MemorySectionName\&quot;:\&quot;None\&quot;,\&quot;MemorySectionChecksum\&quot;:\&quot;None\&quot;}&quot;,&quot;GlobalParameters&quot;:&quot;{\&quot;Name\&quot;:\&quot;Default\&quot;,\&quot;Checksum\&quot;:\&quot;Default\&quot;,\&quot;PerInstancePropertiesChecksum\&quot;:\&quot;\&quot;,\&quot;MemorySectionName\&quot;:\&quot;None\&quot;,\&quot;MemorySectionChecksum\&quot;:\&quot;None\&quot;}&quot;,&quot;InternalData&quot;:&quot;{\&quot;Name\&quot;:\&quot;Default\&quot;,\&quot;Checksum\&quot;:\&quot;Default\&quot;,\&quot;PerInstancePropertiesChecksum\&quot;:\&quot;\&quot;,\&quot;MemorySectionName\&quot;:\&quot;None\&quot;,\&quot;MemorySectionChecksum\&quot;:\&quot;None\&quot;}&quot;,&quot;SharedLocalDataStores&quot;:&quot;{\&quot;Name\&quot;:\&quot;Default\&quot;,\&quot;Checksum\&quot;:\&quot;Default\&quot;,\&quot;PerInstancePropertiesChecksum\&quot;:\&quot;\&quot;,\&quot;MemorySectionName\&quot;:\&quot;None\&quot;,\&quot;MemorySectionChecksum\&quot;:\&quot;None\&quot;}&quot;,&quot;GlobalDataStores&quot;:&quot;{\&quot;Name\&quot;:\&quot;Default\&quot;,\&quot;Checksum\&quot;:\&quot;Default\&quot;,\&quot;PerInstancePropertiesChecksum\&quot;:\&quot;\&quot;,\&quot;MemorySectionName\&quot;:\&quot;None\&quot;,\&quot;MemorySectionChecksum\&quot;:\&quot;None\&quot;}&quot;,&quot;Constants&quot;:&quot;{\&quot;Name\&quot;:\&quot;Default\&quot;,\&quot;Checksum\&quot;:\&quot;Default\&quot;,\&quot;PerInstancePropertiesChecksum\&quot;:\&quot;\&quot;,\&quot;MemorySectionName\&quot;:\&quot;None\&quot;,\&quot;MemorySectionChecksum\&quot;:\&quot;None\&quot;}&quot;,&quot;DataTransfers&quot;:&quot;{\&quot;Name\&quot;:\&quot;Default\&quot;,\&quot;Checksum\&quot;:\&quot;Default\&quot;,\&quot;PerInstancePropertiesChecksum\&quot;:\&quot;\&quot;,\&quot;MemorySectionName\&quot;:\&quot;None\&quot;,\&quot;MemorySectionChecksum\&quot;:\&quot;None\&quot;}&quot;,&quot;ModelData&quot;:&quot;{\&quot;Name\&quot;:\&quot;Default\&quot;,\&quot;Checksum\&quot;:\&quot;Default\&quot;,\&quot;PerInstancePropertiesChecksum\&quot;:\&quot;\&quot;,\&quot;MemorySectionName\&quot;:\&quot;None\&quot;,\&quot;MemorySectionChecksum\&quot;:\&quot;None\&quot;}&quot;,&quot;InitializeTerminate&quot;:&quot;{\&quot;Name\&quot;:\&quot;Default\&quot;,\&quot;Checksum\&quot;:\&quot;Default\&quot;,\&quot;PerInstancePropertiesChecksum\&quot;:\&quot;\&quot;,\&quot;MemorySectionName\&quot;:\&quot;None\&quot;,\&quot;MemorySectionChecksum\&quot;:\&quot;None\&quot;}&quot;,&quot;Execution&quot;:&quot;{\&quot;Name\&quot;:\&quot;Default\&quot;,\&quot;Checksum\&quot;:\&quot;Default\&quot;,\&quot;PerInstancePropertiesChecksum\&quot;:\&quot;\&quot;,\&quot;MemorySectionName\&quot;:\&quot;None\&quot;,\&quot;MemorySectionChecksum\&quot;:\&quot;None\&quot;}&quot;,&quot;SharedUtility&quot;:&quot;{\&quot;Name\&quot;:\&quot;Default\&quot;,\&quot;Checksum\&quot;:\&quot;Default\&quot;,\&quot;PerInstancePropertiesChecksum\&quot;:\&quot;\&quot;,\&quot;MemorySectionName\&quot;:\&quot;None\&quot;,\&quot;MemorySectionChecksum\&quot;:\&quot;None\&quot;}&quot;}</defaultsCMapping>
    <fundamentalSampleTimeOffset>1.0</fundamentalSampleTimeOffset>
    <hasBwsAccessed>true</hasBwsAccessed>
    <hasBwsAccessedByAnyModel>true</hasBwsAccessedByAnyModel>
    <hasConstantOutput>false</hasConstantOutput>
    <hasModelWideEventTs>false</hasModelWideEventTs>
    <isAperiodicRootFcnCallSystem>false</isAperiodicRootFcnCallSystem>
    <isPreCompSingleRate>true</isPreCompSingleRate>
    <isRefModelConstant>true</isRefModelConstant>
    <isRootFcnCallPortGroupsEmpty>true</isRootFcnCallPortGroupsEmpty>
    <loggingSaveFormat>2</loggingSaveFormat>
    <maxFreqHz>-1.0</maxFreqHz>
    <multiThreadingBlockers>#MTCSBlocker_MRConstant</multiThreadingBlockers>
    <numDataInputPorts>0</numDataInputPorts>
    <numLoggableJacobianDStates>0</numLoggableJacobianDStates>
    <numModelWideEventTs>0</numModelWideEventTs>
    <numPortlessSimulinkFunctionPortGroups>0</numPortlessSimulinkFunctionPortGroups>
    <numRuntimeExportedRates>1</numRuntimeExportedRates>
    <numTs>1</numTs>
    <preCompAllowConstTsOnPorts>true</preCompAllowConstTsOnPorts>
    <preCompAllowPortBasedInTriggeredSS>true</preCompAllowPortBasedInTriggeredSS>
    <runtimeNonFcnCallRateInfos type="ModelRefInfoRepo.RateInfo">
      <compiled>true</compiled>
      <isEmpty>true</isEmpty>
      <offset>1.0</offset>
      <period>0.0</period>
      <priority>40</priority>
      <rateIdx>0</rateIdx>
    </runtimeNonFcnCallRateInfos>
    <sampleTimeInheritanceRule>2</sampleTimeInheritanceRule>
    <timingAndTaskingRegistry>&lt;?xml version=&quot;1.0&quot;?&gt;
&lt;slexec_sto version=&quot;1.1&quot; packageUris=&quot;http://schema.mathworks.com/mf0/slexec_mm_sto/R2021a_202007071525&quot;&gt;
  &lt;sto.Registry type=&quot;sto.Registry&quot; uuid=&quot;d71c5c0a-c9d8-4989-ba11-417edddbbdae&quot;&gt;
    &lt;clocks type=&quot;sto.Timer&quot; uuid=&quot;cf87db48-dace-4542-ab37-a38a9d13ab7f&quot;&gt;
      &lt;clockDomain type=&quot;sto.ClockDomain&quot; uuid=&quot;3573cd92-b4a4-4f92-94d5-15995279fb7d&quot;&gt;
        &lt;baseTaskID&gt;_task0&lt;/baseTaskID&gt;
        &lt;rates type=&quot;sto.Rate&quot; uuid=&quot;54419834-cc45-4856-b2cf-315ccfae0796&quot;/&gt;
        &lt;rootTaskHierarchyElements type=&quot;sto.Task&quot; uuid=&quot;9cbcaaad-a4ce-4d66-b974-6d866d46b410&quot;&gt;
          &lt;isExecutable&gt;true&lt;/isExecutable&gt;
          &lt;orderIndex&gt;1&lt;/orderIndex&gt;
          &lt;rates type=&quot;sto.Rate&quot; uuid=&quot;54419834-cc45-4856-b2cf-315ccfae0796&quot;&gt;
            &lt;annotation&gt;FiM&lt;/annotation&gt;
            &lt;colorIndex&gt;8&lt;/colorIndex&gt;
            &lt;description&gt;Fixed in Minor Step&lt;/description&gt;
            &lt;eventSourceType&gt;UNSPECIFIED_EVENT_SOURCE&lt;/eventSourceType&gt;
            &lt;registry type=&quot;sto.Registry&quot; uuid=&quot;d71c5c0a-c9d8-4989-ba11-417edddbbdae&quot;/&gt;
            &lt;taskId&gt;_task0&lt;/taskId&gt;
            &lt;rateSpec type=&quot;sto.RateSpec&quot; uuid=&quot;e002486a-4bc1-4e41-8cfa-353013813649&quot;&gt;
              &lt;offset&gt;1.0&lt;/offset&gt;
              &lt;rateType&gt;ZOHContinuous&lt;/rateType&gt;
            &lt;/rateSpec&gt;
          &lt;/rates&gt;
          &lt;elementType&gt;Task&lt;/elementType&gt;
          &lt;identifier&gt;_task0&lt;/identifier&gt;
          &lt;priority&gt;40&lt;/priority&gt;
        &lt;/rootTaskHierarchyElements&gt;
      &lt;/clockDomain&gt;
    &lt;/clocks&gt;
    &lt;executionSpec&gt;Undetermined&lt;/executionSpec&gt;
    &lt;taskDependencyGraph type=&quot;sto.SerializedTaskConnectionList&quot; uuid=&quot;4fcb7694-dc5d-4f9f-9d29-d9ef43d058ad&quot;&gt;
      &lt;taskIdentifier&gt;_task0&lt;/taskIdentifier&gt;
    &lt;/taskDependencyGraph&gt;
    &lt;taskPriorityDirection&gt;HighNumberLast&lt;/taskPriorityDirection&gt;
    &lt;tasks type=&quot;sto.Task&quot; uuid=&quot;9cbcaaad-a4ce-4d66-b974-6d866d46b410&quot;/&gt;
  &lt;/sto.Registry&gt;
&lt;/slexec_sto&gt;</timingAndTaskingRegistry>
    <usePortBasedSampleTime>false</usePortBasedSampleTime>
    <FMUBlockMap type="ModelRefInfoRepo.FMUBlockInfo" uuid="0ec3c364-9f4c-49e7-9668-04e40791a383"/>
    <codeGenInfo type="ModelRefInfoRepo.CodeGenInformation" uuid="dc91adb0-22fe-41c4-8570-c9713e4bff5c">
      <DWorkTypeName>l1cqubzln1i</DWorkTypeName>
    </codeGenInfo>
    <configSettingsForConsistencyChecks type="ModelRefInfoRepo.ConfigSettingsForConsistencyChecks" uuid="e335b622-2630-48ad-a808-d663127e6a23">
      <consistentOutportInitialization>true</consistentOutportInitialization>
      <frameDiagnosticSetting>2</frameDiagnosticSetting>
      <signalLoggingSaveFormat>2</signalLoggingSaveFormat>
      <simSIMDOptimization>1</simSIMDOptimization>
      <solverName>VariableStepDiscrete</solverName>
      <hardwareSettings type="ModelRefInfoRepo.HardwareSettings" uuid="5f380f05-9c53-4d3e-bb81-40fdf421415e">
        <prodBitPerChar>8</prodBitPerChar>
        <prodBitPerDouble>64</prodBitPerDouble>
        <prodBitPerFloat>32</prodBitPerFloat>
        <prodBitPerInt>32</prodBitPerInt>
        <prodBitPerLong>32</prodBitPerLong>
        <prodBitPerLongLong>64</prodBitPerLongLong>
        <prodBitPerPointer>64</prodBitPerPointer>
        <prodBitPerPtrDiffT>64</prodBitPerPtrDiffT>
        <prodBitPerShort>16</prodBitPerShort>
        <prodBitPerSizeT>64</prodBitPerSizeT>
        <prodEndianess>1</prodEndianess>
        <prodShiftRight>true</prodShiftRight>
        <prodWordSize>64</prodWordSize>
      </hardwareSettings>
    </configSettingsForConsistencyChecks>
    <controllableInputRatesMap type="ModelRefInfoRepo.VarTsUIDMap" uuid="b12181e5-3284-4d46-8058-17b155a7c5c2"/>
    <controllableOutputRatesMap type="ModelRefInfoRepo.VarTsUIDMap" uuid="a1fe3526-ca5a-4c91-bd37-fa122bf67ff7"/>
    <dataPortGroup type="ModelRefInfoRepo.DataPortGroup" uuid="a0511776-82e6-4bad-ac25-a8f87c9f2475"/>
    <expFcnUnconnectedDataPortGroup type="ModelRefInfoRepo.DataPortGroup" uuid="d9e1c39d-ccdc-451b-b210-ead5f29e729e"/>
    <interfaceParameterInfo type="ModelRefInfoRepo.InterfaceParameterInfo" uuid="fd204f8d-2718-4ab6-86ac-68821dc72911"/>
    <messageInfo type="ModelRefInfoRepo.MessageInformation" uuid="5a3d82f4-97b0-4ca1-b64d-4c8c972db08f"/>
    <methodInfo type="ModelRefInfoRepo.MethodExistenceInfo" uuid="3ebc077f-b55c-4c1a-b6a4-67873bc64aeb">
      <hasTerminateMethod>true</hasTerminateMethod>
    </methodInfo>
    <periodicEventPortUnsupportedBlockInfo type="ModelRefInfoRepo.PeriodicEventPortUnsupportedBlockInfo" uuid="f3b3d03d-d0df-45ec-afb1-a12bc361d008"/>
    <portGroupsRequireSameRate type="ModelRefInfoRepo.PortGroupsRequireSameRate" uuid="b10f0f17-d8c1-45f4-96db-01d38db8f750">
      <DSMPortGroups type="ModelRefInfoRepo.NameToPortGroupIdxVectMap" uuid="03d7ea26-93f9-4d25-82d5-bc132a3657fb"/>
      <GlobalDSMPortGroups type="ModelRefInfoRepo.NameToPortGroupIdxVectMap" uuid="30b34c9e-3af7-47bf-96b0-8e0babc44272"/>
      <mergedPortGroups type="ModelRefInfoRepo.NameToPortGroupIdxVectMap" uuid="496a9071-16e6-4725-96a4-daebfd2a814f"/>
    </portGroupsRequireSameRate>
    <rateBasedMdlGlobalDSMRateSpec type="ModelRefInfoRepo.GlobalDSMRateSpecMap" uuid="564ad338-5e62-4af5-82bf-f0a279b14825"/>
    <rateSpecOfGlobalDSMAccessedByDescExpFcnMdlMap type="ModelRefInfoRepo.GlobalDSMRateSpecMap" uuid="ce172abf-e33e-4f50-9d6f-54b083247b60"/>
    <rootBlockDiagramInterface type="ci.Model" uuid="639f9b9a-44db-4b26-9d3e-a1c657b7a720">
      <p_RootComponentInterface type="ci.ComponentInterface" uuid="5e0c78d1-999b-40fa-b854-13721c7abd89">
        <p_Name>Animation_Recorder</p_Name>
        <p_Type>ROOT</p_Type>
      </p_RootComponentInterface>
    </rootBlockDiagramInterface>
    <simulinkFunctions type="ModelRefInfoRepo.SimulinkFunctions" uuid="e789001f-be33-4f1a-809b-2daa29b61413">
      <compSimulinkFunctionCatalog></compSimulinkFunctionCatalog>
    </simulinkFunctions>
    <stateWriterToOwnerMap type="ModelRefInfoRepo.StateWriterInfo" uuid="54392c8e-4386-49c8-8883-2aa97d290c3a"/>
    <stoClientDataRegistry type="sto.ClientDataRegistry" uuid="b2d84c7e-c9dd-4c79-b43d-850f9f8d812a">
      <dataSets type="sto.ClientClockNamedDataSet" uuid="242ccdfd-e6a6-4b97-812b-ce10a8cfd921">
        <tag>sltpEvents</tag>
      </dataSets>
      <dataSets type="sto.ClientTaskHierarchyElementNamedDataSet" uuid="acc5fa1c-cd85-44d1-ac63-631ca0939e30">
        <tag>sltpTaskGroups</tag>
      </dataSets>
      <dataSets type="sto.ClientTaskHierarchyElementNamedDataSet" uuid="6f11da5d-f608-4a68-8e37-8ad82bc2d48d">
        <dSet type="ModelRefInfoRepo.SltpTaskData" uuid="77a9b1b0-f1fd-49aa-9c34-3d467e65b7ba"/>
        <tSet type="ModelRefInfoRepo.SltpTaskData" uuid="77a9b1b0-f1fd-49aa-9c34-3d467e65b7ba">
          <dataName>FiM</dataName>
          <linkedSet type="sto.ClientTaskHierarchyElementNamedDataSet" uuid="6f11da5d-f608-4a68-8e37-8ad82bc2d48d"/>
          <id type="sto.TaskHierarchyElementId">
            <id>_task0</id>
          </id>
        </tSet>
        <tag>sltpTasks</tag>
      </dataSets>
    </stoClientDataRegistry>
    <varTsUIDMap type="ModelRefInfoRepo.VarTsUIDMap" uuid="0a7a1523-8fe8-47f1-9acf-472fccd24230"/>
  </ModelRefInfoRepo.ModelRefInfoRoot>
</MF0>